ChangeLog
MANIFEST.in
README
eggsetup.py
setup.py
configutils/__init__.py
configutils/build.py
configutils/config.py
htmltotext.egg-info/PKG-INFO
htmltotext.egg-info/SOURCES.txt
htmltotext.egg-info/dependency_links.txt
htmltotext.egg-info/native_libs.txt
htmltotext.egg-info/top_level.txt
src/config.h
src/htmlparse.cc
src/htmlparse.h
src/htmlparsetest.cc
src/metaxmlparse.cc
src/metaxmlparse.h
src/myhtmlparse.cc
src/myhtmlparse.h
src/namedentities.h
src/pyhtmltotext.cc
src/safeerrno.h
src/strcasecmp.h
src/utf8convert.cc
src/utf8convert.h
src/utf8itor.cc
src/xapian.h
src/xmlparse.cc
src/xmlparse.h
src/xapian/unicode.h
src/xapian/visibility.h
test/__init__.py
test/test.py