Metadata-Version: 1.0
Name: htmltotext
Version: 0.7
Summary: Extract text and some metainfo from HTML, coping with malformed pages as well as possible.
Home-page: http://code.google.com/p/flaxcode/wiki/HtmlToText
Author: Richard Boulton
Author-email: richard@lemurconsulting.com
License: GPL
Download-URL: http://flaxcode.googlecode.com/files/htmltotext-0.7.tar.gz
Platform: Any
Classifier: Development Status :: 3 - Alpha
Classifier: Intended Audience :: Developers
Classifier: License :: OSI Approved :: GNU General Public License (GPL)
Classifier: Programming Language :: C++
Classifier: Topic :: Internet :: WWW/HTTP :: Indexing/Search
Classifier: Operating System :: MacOS
Classifier: Operating System :: Microsoft
Classifier: Operating System :: POSIX
